aws_assume_role_lib/__init__.py
aws_assume_role_lib/__main__.py
aws_assume_role_lib/aws_assume_role_lib.py
aws_assume_role_lib/py.typed
aws_assume_role_lib-2.10.0.dist-info/LICENSE
aws_assume_role_lib-2.10.0.dist-info/WHEEL
aws_assume_role_lib-2.10.0.dist-info/METADATA
aws_assume_role_lib-2.10.0.dist-info/RECORD
