Metadata-Version: 2.1
Name: aws-assume-role-lib
Version: 2.10.0
Summary: Assumed role session chaining (with credential refreshing) for boto3
Home-page: https://github.com/benkehoe/aws-assume-role-lib
License: Apache-2.0
Author: Ben Kehoe
Author-email: ben@kehoe.io
Requires-Python: >=3.6,<4.0
Classifier: Development Status :: 5 - Production/Stable
Classifier: Intended Audience :: Developers
Classifier: Intended Audience :: System Administrators
Classifier: License :: OSI Approved :: Apache Software License
Classifier: Operating System :: OS Independent
Classifier: Programming Language :: Python :: 3
Classifier: Programming Language :: Python :: 3.10
Classifier: Programming Language :: Python :: 3.6
Classifier: Programming Language :: Python :: 3.7
Classifier: Programming Language :: Python :: 3.8
Classifier: Programming Language :: Python :: 3.9
Classifier: Topic :: Software Development :: Libraries
Classifier: Topic :: Utilities
Requires-Dist: boto3 (>=1.17.51,<2.0.0)
Project-URL: Repository, https://github.com/benkehoe/aws-assume-role-lib
